<?xml version="1.0" encoding="UTF-8"?>
<tv>
  <channel id="ch3.th"><display-name>Ch3</display-name></channel>
  <channel id="Thairath TV"><display-name>Thairath TV</display-name></channel>
  <channel id="mono29.th"><display-name>Mono29</display-name></channel>
  <channel id="ch5.th"><display-name>ch5</display-name></channel>
  <channel id="GMM25.th"><display-name>GMM25</display-name></channel>
  <channel id="One31"><display-name>One31</display-name></channel>
  <channel id="ch8.th"><display-name>Ch8</display-name></channel>
  <channel id="workpiont.th"><display-name>Workpoint</display-name></channel>
  <channel id="ThaiPBS"><display-name>Thai PBS</display-name></channel>
  <channel id="MCOT"><display-name>MCOT</display-name></channel>

  <programme start="20260215150000 +0700" stop="20260215180000 +0700" channel="ch3.th"><title lang="th">รายการช่อง 3</title></programme>
  <programme start="20260215150000 +0700" stop="20260215180000 +0700" channel="Thairath TV"><title lang="th">รายการไทยรัฐทีวี</title></programme>
  <programme start="20260215150000 +0700" stop="20260215180000 +0700" channel="mono29.th"><title lang="th">รายการ Mono29</title></programme>
  <programme start="20260215150000 +0700" stop="20260215180000 +0700" channel="ch5.th"><title lang="th">รายการช่อง 5</title></programme>
  <programme start="20260215150000 +0700" stop="20260215180000 +0700" channel="GMM25.th"><title lang="th">รายการ GMM25</title></programme>
  <programme start="20260215150000 +0700" stop="20260215180000 +0700" channel="One31"><title lang="th">รายการช่อง One31</title></programme>
  <programme start="20260215150000 +0700" stop="20260215180000 +0700" channel="ch8.th"><title lang="th">รายการช่อง 8</title></programme>
  <programme start="20260215150000 +0700" stop="20260215180000 +0700" channel="workpiont.th"><title lang="th">รายการเวิร์คพอยท์</title></programme>
  <programme start="20260215150000 +0700" stop="20260215180000 +0700" channel="ThaiPBS"><title lang="th">รายการ Thai PBS</title></programme>
  <programme start="20260215150000 +0700" stop="20260215180000 +0700" channel="MCOT"><title lang="th">รายการช่อง MCOT</title></programme>
</tv>>
